[{"attendance":"Not Mandatory","clarityColor":"average","easyColor":"poor","helpColor":"average","helpCount":0,"id":22768138,"notHelpCount":0,"onlineClass":"","quality":"average","rClarity":2,"rClass":"GEOG1000","rComments":"very unorganized, BORING, and immature. doesn't know how to teach. treats the students like elementary schoolers. easy grade if you show up and can manage to stay awake, both of which are excruciatingly painful.","rDate":"01/18/2014","rEasy":1,"rEasyString":"1.0","rErrorMsg":null,"rHelpful":3,"rInterest":"Meh","rOverall":2.5,"rOverallString":"2.5","rStatus":1,"rTextBookUse":"No","rWouldTakeAgain":"N/A","sId":1078,"takenForCredit":"N/A","teacher":null,"teacherGrade":"B+","teacherRatingTags":[],"unUsefulGrouping":"people","usefulGrouping":"people"}]