[{"attendance":"N/A","clarityColor":"good","easyColor":"good","helpColor":"good","helpCount":0,"id":15421863,"notHelpCount":0,"onlineClass":"","quality":"awesome","rClarity":4,"rClass":"CHEM122","rComments":"I took Chem 122 with Don. This is a instrumental Analysis class that will teach you how to write a paper in a scientific mannaer. Don has high expectation and his grading is harsh. But it is worth taking the class with him cause you will learn A LOT. He is very approachable and freindly and eager to help.","rDate":"01/28/2009","rEasy":4,"rEasyString":"4.0","rErrorMsg":null,"rHelpful":5,"rInterest":"Sorta interested","rOverall":4.5,"rOverallString":"4.5","rStatus":1,"rTextBookUse":"No","rWouldTakeAgain":"N/A","sId":1078,"takenForCredit":"N/A","teacher":null,"teacherGrade":"N/A","teacherRatingTags":[],"unUsefulGrouping":"people","usefulGrouping":"people"}]