[{"attendance":"N/A","clarityColor":"good","easyColor":"poor","helpColor":"good","helpCount":0,"id":13346813,"notHelpCount":0,"onlineClass":"","quality":"awesome","rClarity":4,"rClass":"PHYE30J","rComments":"Great class for beginners. The majority of each class was spent weight lifting, but there was always time left for a brief cardio workout. Danielle was a knowledgeable and friendly trainer.","rDate":"07/22/2007","rEasy":1,"rEasyString":"1.0","rErrorMsg":null,"rHelpful":5,"rInterest":"Really into it","rOverall":4.5,"rOverallString":"4.5","rStatus":1,"rTextBookUse":"No","rWouldTakeAgain":"N/A","sId":1078,"takenForCredit":"N/A","teacher":null,"teacherGrade":"N/A","teacherRatingTags":[],"unUsefulGrouping":"people","usefulGrouping":"people"},{"attendance":"N/A","clarityColor":"good","easyColor":"average","helpColor":"good","helpCount":0,"id":12252898,"notHelpCount":0,"onlineClass":"","quality":"awesome","rClarity":5,"rClass":"PHYE30","rComments":"Danielle is great, very nice and friendly. She makes working out fun and different everytime. She has an endless library of knowledge and type of workouts. Accomodating to all workout levels. I enjoyed the class very much, it gave me new and improved perspective of weight training after years of it since high school.","rDate":"09/27/2006","rEasy":2,"rEasyString":"2.0","rErrorMsg":null,"rHelpful":5,"rInterest":"It's my life","rOverall":5,"rOverallString":"5.0","rStatus":1,"rTextBookUse":"No","rWouldTakeAgain":"N/A","sId":1078,"takenForCredit":"N/A","teacher":null,"teacherGrade":"N/A","teacherRatingTags":[],"unUsefulGrouping":"people","usefulGrouping":"people"}]